{
  "generatedAt": "2025-07-01T11:22:46.560830",
  "jobSeeker": {
    "name": "김구인",
    "age": 65,
    "location": "서울 특별시 강남구",
    "available_time": "월화 수목 금토일 24시간",
    "license": [],
    "preferred_field": [
      "교통안전"
    ],
    "health_condition": "없습니다.",
    "career": "교통 업무를 담당하는 녹색 어머니회에서 10년간 일했습니다.",
    "education": "고등학교 졸업했습니다."
  },
  "recommendations": [
    {
      "rank": 1,
      "unifiedScore": 0.529,
      "reason": "보라매병원역은 강남구에서 비교적 가까운 위치이며, 도시철도 신림선 본사 건물 미화원은 특별한 자격증 없이도 지원 가능합니다. 10년간 녹색어머니회 활동을 통해 얻은 성실함과 책임감을 바탕으로 건물 미화 업무를 수행하실 수 있을 것으로 판단됩니다.",
      "jobPosting": {
        "title": "[보라매병원역 인근] 도시철도 신림선 본사 건물 미화원 모집",
        "company": "그린환경테크 주식회사",
        "address": "04797 서울특별시 성동구 성수이로 118 (성수동2가, 성수아카데미타워)",
        "distanceKm": 3.23,
        "details": "-"
      }
    },
    {
      "rank": 2,
      "unifiedScore": 0.5123,
      "reason": "압구정로데오역은 희망 지역인 강남구에 위치하고 있습니다. 병원 미화 업무는 깨끗하고 안전한 환경을 유지하는 데 중요한 역할을 하며, 평소 건강 관리에 힘쓰셨다면 충분히 감당하실 수 있습니다. 소독 업무는 꼼꼼함과 책임감이 중요하며, 10년간 녹색어머니회 활동 경험을 통해 보여주신 책임감이 이 직무에 적합하다고 판단됩니다.",
      "jobPosting": {
        "title": "[압구정로데오역 3번출구] 병원 *워싱담당(소독) 미화* 모집 (1명)",
        "company": "주식회사삼오종합관리",
        "address": "04735 서울특별시 성동구 한림말길 41-21 (옥수동, 삼오빌딩)",
        "distanceKm": 3.89,
        "details": "-"
      }
    },
    {
      "rank": 3,
      "unifiedScore": 0.5115,
      "reason": "기흥은 강남구에서 다소 거리가 있지만, 현대모비스기술연구소는 안정적인 근무 환경을 제공할 가능성이 높습니다. 미화원은 특별한 자격증 없이 지원 가능하며, 10년간 녹색어머니회 활동을 통해 얻은 성실함과 책임감을 바탕으로 건물 미화 업무를 수행하실 수 있을 것으로 판단됩니다.",
      "jobPosting": {
        "title": "[기흥 마북동] 현대모비스기술연구소 내 미화원 채용",
        "company": "에프엠파트너주식회사",
        "address": "06258 서울특별시 강남구 도곡로2길 10, 503호 뱅뱅별관 503호 (도곡동)",
        "distanceKm": 3.39,
        "details": "-"
      }
    },
    {
      "rank": 4,
      "unifiedScore": 0.5108,
      "reason": "압구정로데오역은 희망 지역인 강남구에 위치하고 있습니다. 성형외과 세탁 담당 미화는 깨끗하고 위생적인 환경을 유지하는 데 중요한 역할을 하며, 꼼꼼함과 성실함이 요구됩니다. 10년간 녹색어머니회 활동을 통해 보여주신 책임감과 성실함이 이 직무에 적합하다고 판단됩니다.",
      "jobPosting": {
        "title": "[성형외과] 압구정로데오역 인근 *세탁담당 미화* 모집 (1명)",
        "company": "주식회사삼오종합관리",
        "address": "04735 서울특별시 성동구 한림말길 41-21 (옥수동, 삼오빌딩)",
        "distanceKm": 3.89,
        "details": "-"
      }
    },
    {
      "rank": 5,
      "unifiedScore": 0.5108,
      "reason": "압구정로데오역은 희망 지역인 강남구에 위치하고 있습니다. 해당 공고는 3번 공고와 동일한 내용으로 판단됩니다. 성형외과 세탁 담당 미화는 깨끗하고 위생적인 환경을 유지하는 데 중요한 역할을 하며, 꼼꼼함과 성실함이 요구됩니다. 10년간 녹색어머니회 활동을 통해 보여주신 책임감과 성실함이 이 직무에 적합하다고 판단됩니다.",
      "jobPosting": {
        "title": "[성형외과] 압구정로데오역 인근 *세탁담당 미화* 모집 (1명)",
        "company": "주식회사삼오종합관리",
        "address": "04735 서울특별시 성동구 한림말길 41-21 (옥수동, 삼오빌딩)",
        "distanceKm": 3.89,
        "details": "-"
      }
    },
    {
      "rank": 6,
      "unifiedScore": 0.5078,
      "reason": "우리W타워는 강남구에 위치해 있을 가능성이 높으며, 보안대원은 특별한 기술 없이도 성실함과 책임감으로 수행할 수 있는 업무입니다. 2인 1조 근무이므로 업무 부담이 적을 수 있습니다. 녹색어머니회 활동을 통해 얻은 봉사정신과 책임감을 바탕으로 안전하게 근무하실 수 있을 것으로 기대됩니다.",
      "jobPosting": {
        "title": "우리W타워 보안대원 모십니다.(주주,야야,비비 2인1조 3교대)",
        "company": "(주）우리휴먼서비스",
        "address": "04783 서울특별시 성동구 연무장11길 10 (성수동2가, 우리큐브)",
        "distanceKm": 2.98,
        "details": "-"
      }
    },
    {
      "rank": 7,
      "unifiedScore": 0.5049,
      "reason": "동인천역은 희망 지역과 거리가 멀어 추천하기 어렵습니다.",
      "jobPosting": {
        "title": "[동인천역] 은행 미화원 구인",
        "company": "(주）우리휴먼서비스",
        "address": "04783 서울특별시 성동구 연무장11길 10 (성수동2가, 우리큐브)",
        "distanceKm": 2.98,
        "details": "-"
      }
    },
    {
      "rank": 8,
      "unifiedScore": 0.5041,
      "reason": "강남구 삼성동은 희망 지역과 일치하며, 현대빌라 관리원은 격일제 근무로 체력적인 부담을 줄일 수 있습니다. 빌라 관리 업무는 평소 꼼꼼하고 성실한 성격을 가지신 분에게 적합하며, 10년간 녹색어머니회 활동을 통해 보여주신 책임감과 성실함이 이 직무에 도움이 될 것입니다.",
      "jobPosting": {
        "title": "[강남구 삼성동] 현대빌라2차 주간 격일제 근무 관리원 모집",
        "company": "(주)삼오관리",
        "address": "04735 서울특별시 성동구 한림말길 41-21 (옥수동, 삼오빌딩)",
        "distanceKm": 3.89,
        "details": "-"
      }
    },
    {
      "rank": 9,
      "unifiedScore": 0.4934,
      "reason": "잠실동은 강남구와 인접한 지역이며, 금비빌딩 시설관리원은 격일제 근무로 체력적인 부담을 줄일 수 있습니다. 시설관리 업무는 건물 내 간단한 수리 및 점검을 포함할 수 있으며, 평소 꼼꼼하고 성실한 성격을 가지신 분에게 적합합니다.",
      "jobPosting": {
        "title": "[잠실동] 금비빌딩 격일 시설관리원 모집 (월 250만원)",
        "company": "(주)맥풍",
        "address": "06532 서울특별시 서초구 신반포로45길 9-22 (잠원동, 천우빌딩)",
        "distanceKm": 2.67,
        "details": "-"
      }
    },
    {
      "rank": 10,
      "unifiedScore": 0.4913,
      "reason": "고촌읍 신곡리는 희망 지역과 거리가 멀어 추천하기 어렵습니다.",
      "jobPosting": {
        "title": "고촌읍 신곡리 인근 건설 현장 격일제 경비원 채용",
        "company": "국도안전관리(주)",
        "address": "06695 서울특별시 서초구 방배로 73 (방배동, 양지빌딩 4층)",
        "distanceKm": 5.98,
        "details": "-"
      }
    }
  ]
}